{
    "1904": [
        "Ruskin",
        "Gandhi"
    ],
    "1906": [
        "Jan Christiaan Smuts",
        "Gandhi"
    ],
    "1908": [
        "Smuts",
        "Mir Alam",
        "Gandhi"
    ],
    "1910": [
        "Herman Kallenbach",
        "Gandhi",
        "Tolstoy",
        "Kallenbach"
    ],
    "1912": [],
    "1913": [
        "Pearson",
        "Kasturba",
        "C.F. Andrews",
        "Gandhi",
        "Kallenbach"
    ],
    "1914": [
        "Mr Hult",
        "Bill"
    ],
    "1915": [
        "Gopal Krishna Gokhale",
        "Laxmi",
        "Gokhale",
        "Gandhi"
    ],
    "1916": ["Jawaharlal Nehru"],
    "1917": [
        "Dharnidhar Prasad",
        "Acharya Kriplani",
        "Gandhi",
        "Anugrah Narayan Singh",
        "Simon",
        "Mahatma Gandhi",
        "Frank Shy",
        "C. F. Andrews",
        "Motihari",
        "Raj Kishore Prasad",
        "Mahadev Desai",
        "Rajkumar Shukla",
        "Rajendra Prasad",
        "H. S. Pollock",
        "Mahadev Desai"
    ]
}