{
    "1944": [
        "Vincent Smith",
        "Charak",
        "Hastinapur",
        "Mahendra",
        "Gandhiji",
        "Gordon Childe",
        "Narada",
        "John Marshall",
        "Rati",
        "William",
        "Chand Bibi",
        "Palibothra",
        "Rita",
        "Vasanta",
        "Kalhana",
        "Fick",
        "Twashtri",
        "Vikramaditya",
        "Kautilya",
        "Signor Mussolini",
        "Antiochus",
        "Bertrand Russell",
        "Michelet",
        "Tilak",
        "Nikator",
        "Strabo",
        "Joan",
        "Dodwell",
        "Manu",
        "Shahnamah",
        "Shaka",
        "Childe",
        "Winternitz",
        "Bindusara",
        "Cyrene",
        "Auguste Comte",
        "Gandhari",
        "Patna",
        "Holy Writ",
        "Alice",
        "Kalingas",
        "Bhagalpur",
        "Gupta",
        "Advaita",
        "Arabian Sea",
        "Max M\u00fcller",
        "Aurobindo Ghose",
        "Sushruta",
        "Kanishka",
        "Milinda",
        "Aquna",
        "Macdonell",
        "Swami Vivekananda",
        "Romain Rolland",
        "Rabindranath Tagore",
        "Sanghamitra",
        "Mahavira",
        "Indianized",
        "Firdusi",
        "Chandragupta",
        "Sindhu",
        "Macnicol",
        "Harappa",
        "Arrian",
        "Chanakya",
        "Ananda",
        "Birbal",
        "Megasthenes"
    ],
    "1935": [
        "Bex",
        "Signor Mussolini",
        "Chitra",
        "Kamala",
        "Badenweiler",
        "Indira"
    ],
    "1936": [
        "Hardwar",
        "Bharat Mata",
        "Childe",
        "Sindhu"
    ],
    "1937": [
        "Samkhya",
        "Kalidasa",
        "Lilavati",
        "Budh",
        "Johnstone",
        "Jayavarman",
        "Joseph Wood Krutch",
        "Shakas",
        "Sebokht",
        "Shastras",
        "Srivijaya",
        "Shudraka",
        "Hogben",
        "Heliodorus",
        "Bhavbhuti",
        "Milinda",
        "Mihiragula",
        "Mihira Bhoja",
        "Romain Rolland",
        "Sailendra",
        "Dion",
        "Chanakya",
        "Turco-Mongols",
        "Kumarajiva",
        "Majapahit",
        "Nagarjuna",
        "Monsieur Grousset",
        "Svarnabhumi",
        "Mrichhkatika",
        "William",
        "Havell",
        "Absolute Soul",
        "Richard Garbe",
        "Apastamba",
        "Bhasa",
        "Nyaya",
        "Majumdar",
        "Andhras",
        "Rajendra",
        "Murari",
        "Tughlak",
        "Sylvain L\u00e9vi",
        "Buddhabhadra",
        "Angkor Vat",
        "Arthur Waley",
        "Ibn Batuta",
        "Shon Wen",
        "Bhagalpur",
        "Jinabhadra",
        "Max M\u00fcller",
        "Aurobindo Ghose",
        "Srinivasa Ramanujam",
        "William Jones",
        "Rawlinson",
        "Yashovarman",
        "Ashvaghosa",
        "Katyayana",
        "Kublai Khan",
        "Kucha",
        "Jinagupta",
        "Shunya",
        "Madhyamika",
        "Aryan India",
        "Kushan",
        "Bhaskara II",
        "Apollonius",
        "Yuan Chwang",
        "Shankara",
        "Darius",
        "Vikramaditya",
        "Samudragupta",
        "Hsuan Tsang",
        "Baladitya",
        "Antiochus",
        "Brahmagupta",
        "Manu",
        "Osbert Sitwell",
        "Satyakama Jabala",
        "Gupta",
        "Shiva Nataraja",
        "Kanishka",
        "Sthavira Prajnadeva",
        "Rabindranath Tagore",
        "Indianized",
        "Chuang",
        "Rajashekhara",
        "Santiniketan",
        "Patanjali",
        "Henry Maine",
        "John Marshall",
        "Charles Eliot",
        "Shilabhadra",
        "Lawrence Binyon",
        "Prayaga",
        "Palembang",
        "Bhavabhuti",
        "Ashvaghosha",
        "Kanauj",
        "Dodds",
        "Yavanas",
        "Fahien",
        "Julian Huxley",
        "Dodwell",
        "Ryder",
        "Bindusara",
        "Keith",
        "Harshavardhana",
        "Humayun",
        "Anacreon",
        "Dantzig",
        "Sylvain Levi",
        "James Darmesteler",
        "Severus",
        "Matanga",
        "Hien",
        "K\u00e2lid\u00e2sa",
        "Hardwar",
        "Halsted",
        "Chandragupta",
        "Stcherbatsky",
        "Alberuni",
        "Megasthenes",
        "Urwick"
    ],
    "1820": [
        "Nicolo Conti",
        "Paes",
        "Chengiz Khan",
        "Ibn Sina",
        "George Birdwood",
        "Charles II",
        "Sher Shah",
        "Warren Hastings",
        "Fyzee",
        "Liddell Hart",
        "Selfsufficiency",
        "James II",
        "Rashid",
        "Shah Jehan",
        "Firdausi",
        "Raja Man Singh",
        "Charles Metcalfe",
        "Omar Khayyam",
        "Gandhiji",
        "Francis",
        "Havell",
        "Ahmad Shah Durrani",
        "Edward Thompson",
        "Maharaja Ranjit Singh",
        "Tughlak",
        "Nizam",
        "Shahnamah",
        "Mewar",
        "Idrisi",
        "Ibn Batuta",
        "Alauddin Khilji",
        "Jenghiz",
        "Jaichandra",
        "Holkar",
        "Abdul Fazl",
        "Amir Khusrau",
        "Mary Beard",
        "Khalifas",
        "Macdonell",
        "Adam Smith",
        "Gama",
        "Prinsep",
        "Him",
        "Tulsidas",
        "Sultan Mahmud",
        "Shivaji",
        "Emmanuel",
        "Chand Bibi",
        "Nana Farnavis",
        "Mughal Viceroy",
        "Allawardi",
        "Ferghana",
        "Guru Nanak",
        "Rumi",
        "Prithvi Raj Chauhan",
        "Rana Pratap",
        "Al Khwarismi",
        "Mencius",
        "Ahilya Bai",
        "Manak",
        "Barmak",
        "Marco",
        "Harun",
        "Indianized",
        "Louis XIV",
        "Shukracharya",
        "Vasco",
        "Lodi",
        "Tipu Sultan",
        "Haider Ali",
        "Ibn Rushd",
        "Hulagu",
        "Aurungzeb",
        "Jehangir",
        "Bhairu",
        "George III",
        "Kanauj",
        "Tilak",
        "Jahiliyat",
        "Mahadaji",
        "Charles Martel",
        "Murshidabad",
        "Kabir",
        "Abu Nasr Farabi",
        "Abdul Rahim Khankhana",
        "John Shore",
        "Jacquemont",
        "Sawai Jai Singh",
        "Queen Elizabeth",
        "Feroze",
        "Alberuni",
        "Birbal"
    ],
    "1857": [
        "Munshi Zakaullah",
        "Shivaji",
        "Brooke Adams",
        "Maulana Shibli Nomani",
        "William",
        "Aurungzeb",
        "Marwaris",
        "Nazir Ahmad",
        "Dadabhai",
        "John Bright",
        "Gopal Krishna Gokhale",
        "Abdul Kalam Azad",
        "Raja Ram Mohan Roy",
        "Kashmiri Brahmin",
        "Edward Thompson",
        "Abul Kalam Azad",
        "Iqbal",
        "Maharaja Ranjit Singh",
        "Tilak",
        "William Bentinck",
        "Nizam",
        "Savarkar",
        "Charles II",
        "Manu",
        "Khojas",
        "Bohras",
        "Hali",
        "Montgomery Martin",
        "Crompton",
        "Kaye",
        "Swami Dayananda Saraswati",
        "Garrett",
        "Jallianwala Bagh",
        "Advaita",
        "Drisadvati",
        "William Jones",
        "Sanyasin",
        "Kemal Pasha",
        "Ramakrishna Paramahansa",
        "Rabindranath Tagore",
        "Swami Vivekananda",
        "Romain Rolland",
        "Bikaner",
        "Bahadur Shah",
        "Syed Chirag Ali",
        "Bal Gangadhar Tilak",
        "Ghalib",
        "Lord Bentinck",
        "Charles Metcalfe",
        "Muhammad Tughlaq",
        "Shaukat Ali",
        "Chaitanya",
        "Munshi Karamat Ali",
        "Jamshedji Tata",
        "Annie",
        "Tipu Sultan",
        "Shelvankar",
        "Lakshmi Bai",
        "Buckingham",
        "Neill",
        "Ansari"
    ],
    "1942": [
        "Badshah",
        "Spykman",
        "Gandhiji",
        "Lao Tzu",
        "Winston Churchill",
        "Rajendra",
        "John Stuart Mill",
        "Yugadharma",
        "Janaka",
        "Sabha",
        "Kampf",
        "Yajnavalka",
        "Aurobindo Ghose",
        "Krishak",
        "Lloyd George",
        "Linlithgow",
        "Jim",
        "Rabindranath Tagore",
        "Maulana Abul Kalam Azad",
        "Wendell Wilkie",
        "Him",
        "Prasad",
        "Melos",
        "Bernard Shaw",
        "Abdul Ghaffar Khan",
        "Jamshedji Tata",
        "Manchukuo",
        "Reginald",
        "John Mathai"
    ],
    "1939": [
        "Subhas Bose",
        "Keith",
        "Abul Kalam Azad",
        "Gandhiji",
        "Stafford Cripps",
        "Locarno",
        "Madame Chiang Kaishek",
        "Bernard Shaw",
        "Rafi",
        "Linlithgow",
        "Berriedale Keith",
        "Winston Churchill",
        "Shri",
        "Rabindranath Tagore",
        "Maulana Abul Kalam Azad"
    ]
}