{
    "1": {
        "1": [
            "North Carolina",
            "Exeter",
            "Indian",
            "Indiana",
            "Riney",
            "Abraham",
            "Isaac",
            "Caleb Hazel",
            "Abraham Lincoln",
            "William Brum\ufb01eld",
            "Mr. Lincoln",
            "Atherton",
            "Harrison County",
            "West",
            "Hingham",
            "Christian",
            "Quakers",
            "Larue County",
            "Reading",
            "Jacob",
            "East",
            "Tennessee",
            "Samuel",
            "Mordecai",
            "Floyd",
            "Shiny Mountain",
            "Bullitt County",
            "Zachariah",
            "Uncle Isaac",
            "Ralph Crume",
            "John",
            "Virginia",
            "Mr.",
            "Thompson",
            "Christianity",
            "Sarah",
            "Taunton",
            "Daniel Boone",
            "Kentucky",
            "Nancy Hanks",
            "Josiah",
            "William Penn",
            "Blue Ball",
            "Spencer County",
            "Pennsylvania",
            "Nancy",
            "New Englanders",
            "Ferry",
            "Missouri",
            "Hancock County",
            "England",
            "Gray",
            "Wataga",
            "Mary",
            "South Carolina",
            "Larue",
            "Knob Creek",
            "New England",
            "Nancy Lincoln",
            "Daniel",
            "American",
            "Elegy",
            "Hodgenville",
            "Nashville",
            "Lincoln",
            "Baptist",
            "Rockingham County",
            "Bardstown",
            "Hardin County",
            "Massachusetts",
            "Parson Elkin",
            "Berks County",
            "Eastern",
            "Nolin Creek",
            "Thomas",
            "Public",
            "Illinois",
            "Creek",
            "United States",
            "Washington County",
            "Mr. Riney",
            "Thomas Lincoln"
        ],
        "2": [
            "Weems",
            "State",
            "Night",
            "Gentryville",
            "Henry Clay",
            "God",
            "Parson Elkin",
            "English",
            "Indiana",
            "Abundant",
            "Mr.",
            "Andrew",
            "Abraham",
            "John Bunyan",
            "Abraham Lincoln",
            "Lincolns",
            "Elizabethtown",
            "Fables",
            "Trenton",
            "Washington",
            "Sally Johnston",
            "Nancy Lincoln",
            "Thomas",
            "Mr. Lincoln",
            "Nature",
            "Christian",
            "Crawford",
            "Pilgrim",
            "Ramsay",
            "Natchez",
            "Azel W. Dorsey",
            "Mississippi",
            "American",
            "Andrew Crawford",
            "Kentucky",
            "New Orleans",
            "Franklin",
            "Mr. Seward",
            "Mr. Sweeney",
            "Lincoln",
            "New Jersey",
            "Thomas Lincoln",
            "Neighbor",
            "Mr. Crawford"
        ],
        "3": [
            "Mr. Taylor",
            "Grove",
            "Honest Abe",
            "Aaron Grigsby",
            "Sangamon",
            "New Salem",
            "Menard County",
            "Menard",
            "English",
            "Indiana",
            "Dennis",
            "Mr.",
            "Abraham",
            "John D. Johnston",
            "Petersburg",
            "Lexington",
            "Mr. Green",
            "Coles County",
            "Johnston",
            "Abraham Lincoln",
            "Brown",
            "Macon County",
            "Mr. Brown",
            "Jack Armstrong",
            "Mr. Lincoln",
            "Sarah",
            "Nancy Miller",
            "Denton O\ufb00utt",
            "O\ufb00utt",
            "Money",
            "Grove Boys",
            "Illinois",
            "Denton",
            "Kentucky",
            "Strange",
            "Sangamon River",
            "Mr. Linken",
            "John Hanks",
            "County",
            "Hanks",
            "Spring\ufb01eld",
            "Kirkham",
            "Hale",
            "Lincoln",
            "Decatur",
            "Thomas Lincoln",
            "Galena",
            "Armstrong",
            "Green"
        ],
        "4": [
            "Grove",
            "Greene",
            "New Salem",
            "Mr. Speaker",
            "Ferry",
            "Rock River",
            "William",
            "Menard County",
            "Sangamon County",
            "Indian",
            "Henry Clay",
            "Kirkpatrick",
            "Calhoun",
            "Gibson",
            "John",
            "Captain Lincoln",
            "Flint",
            "Mr.",
            "Dixon",
            "Black Hawk",
            "Indians",
            "Abraham Lincoln",
            "Mr. Clay",
            "Hawk",
            "Colonel",
            "Winnebagoes",
            "Defeat",
            "Thompson",
            "Hull",
            "Mr. Greene",
            "Petersburgh",
            "Rock Island",
            "Mr. Lincoln",
            "Jackson",
            "Black",
            "O\ufb00utt",
            "Party",
            "Radford",
            "Mr. Kirkpatrick",
            "Mississippi",
            "Grove Boys",
            "James Short",
            "Ottowa",
            "Illinois",
            "United States",
            "Reynolds",
            "Pottawatomies",
            "Zachary Taylor",
            "Tennessee",
            "Reuben Radford",
            "Stuart",
            "Jonathan H.",
            "Berry",
            "Spring\ufb01eld",
            "Kansas",
            "Peoria",
            "Lincoln",
            "Captain",
            "Galena",
            "Joseph Duncan",
            "John Calhoun",
            "Clary",
            "Prophetstown"
        ],
        "5": [
            "Yates",
            "Greene",
            "New Salem",
            "William",
            "Henry Clay",
            "God",
            "far-sighted",
            "Richard Yates",
            "Indiana",
            "Shakspeare",
            "Mr.",
            "Abraham Lincoln",
            "Mr. Greene",
            "Daniel Webster",
            "O\ufb00utt",
            "Christian",
            "Burns",
            "Illinois",
            "William G. Greene",
            "Denton",
            "United States",
            "Kentuckian",
            "Lincoln",
            "Captain",
            "Cunning"
        ],
        "6": [
            "Ninian",
            "John J. Hardin",
            "Sangamon",
            "St. Louis",
            "New Salem",
            "Sangamon County",
            "Jesse K. Dubois",
            "Menard",
            "New Sale",
            "William A. Richardson",
            "Mr.",
            "Abraham",
            "Dan Stone",
            "Coles County",
            "Colonel",
            "Vandalia",
            "Douglas",
            "William McMurtny",
            "Michigan Canal Company",
            "James Shields",
            "Mr. Lincoln",
            "John Hogan",
            "John Dement",
            "James Semple",
            "Mr. Douglas",
            "Edwards",
            "American",
            "Illinois",
            "United States",
            "Robert Smith",
            "Newton Cloud",
            "John T. Stuart",
            "Stuart",
            "Spring\ufb01eld",
            "Lincoln",
            "Stephen A. Douglas",
            "John Moore",
            "Chicago",
            "James"
        ],
        "7": [
            "Allusion",
            "New Salem",
            "Major Stuart",
            "English",
            "Mr.",
            "Abe Lincoln",
            "Mr. Van Buren",
            "Colonel",
            "Wabash",
            "Vandalia",
            "Speaker",
            "Mr. Lincoln",
            "Good",
            "Christian",
            "Wabash County",
            "Grove Boys",
            "Mr. Stuart",
            "Illinois",
            "East",
            "Stuart",
            "Spring\ufb01eld",
            "Ewing",
            "William Butler",
            "Lincoln",
            "mid-passage",
            "Hon"
        ],
        "8": [
            "Shields",
            "Gallantry",
            "Wallace",
            "Mr. Polk",
            "Mr. Shields",
            "Henry Clay",
            "Missouri",
            "Bloody Island",
            "Mr. Constable",
            "Indiana",
            "Linder",
            "Mr.",
            "Davis",
            "Lexington",
            "Mr. Clay",
            "Chicago",
            "Miss E.",
            "Vandalia",
            "Speed",
            "Robert",
            "Baker",
            "Simeon Francis",
            "Beck",
            "Clay",
            "Paris",
            "James Shields",
            "Mr. Lincoln",
            "Louisville",
            "Miss Mary Todd",
            "Miss",
            "Constable",
            "American",
            "Mr. Cogdal",
            "Illinois",
            "Mr. Stuart",
            "United States",
            "Kentucky",
            "Francis",
            "Kentuckian",
            "Henry",
            "Ashland",
            "Spring\ufb01eld",
            "Lincoln",
            "Hon",
            "Much",
            "Mr. Francis"
        ],
        "9": [
            "Particularity",
            "Marshall",
            "Taylor",
            "Mexico",
            "Bourbon County",
            "Texan",
            "Mr. Defrees",
            "Lower California",
            "Baker",
            "Douglas",
            "Santa Anna",
            "Mr. Lincoln",
            "Guadalupe Hidalgo",
            "Party",
            "France",
            "Abel",
            "Mr. Allison",
            "Cass",
            "Spring\ufb01eld",
            "Mr. Gott",
            "Henry W. Hilliard",
            "Mr. Butter\ufb01eld",
            "Mr. Chairman",
            "New York",
            "Texas",
            "Such",
            "John",
            "Mr.",
            "History",
            "Mr. Clay",
            "Santa",
            "Mississippi",
            "Kentucky",
            "Jacob Collamer",
            "August",
            "Western",
            "Alexander H. Stephens",
            "Slavery",
            "March",
            "Again",
            "Mr. Polk",
            "Polk",
            "Mr. Wentworth",
            "Morrison",
            "Quincy Adams",
            "Clay",
            "Niles",
            "Nueces",
            "New England",
            "Men",
            "American",
            "Louisiana",
            "Hardin",
            "Lincoln",
            "Georgetown",
            "John Quincy Adams",
            "Business",
            "Massachusetts",
            "Mexican",
            "George Ashmun",
            "Linder",
            "District",
            "Coles County",
            "Mr. Richardson",
            "Spain",
            "Columbia",
            "Thomas Butler King",
            "Washington",
            "Wilson",
            "Sabine",
            "Anna",
            "Simple",
            "Samuel F. Vinton",
            "Illinois",
            "Van Buren",
            "United States",
            "Mr. Seaton",
            "Stephen A. Douglas",
            "Robert Toombs",
            "Joshua R. Giddings",
            "Treat"
        ],
        "10": [
            "Allusion",
            "Herndon",
            "God",
            "Joel A. Matteson",
            "Lincoln Herndon",
            "Euclid",
            "Great",
            "Mexico",
            "Mr.",
            "Divine Providence",
            "Maine",
            "South Carolina",
            "Finally",
            "Jack",
            "Matteson",
            "Jack Armstrong",
            "Douglas",
            "Washington",
            "Edward D. Baker",
            "North",
            "James Shields",
            "Mr. Lincoln",
            "McHenry",
            "David Davis",
            "Americans",
            "Mr. Trumbull",
            "South",
            "north-west",
            "Mr. Herndon",
            "Mr. Douglas",
            "Ottawa",
            "My",
            "Thomas Drummond",
            "Grove Boys",
            "American",
            "Illinois",
            "Tribune",
            "United States",
            "Kentucky",
            "Lyman Trumbull",
            "Bloomington",
            "August",
            "Ashland",
            "Henry",
            "California",
            "Kansas",
            "Caton",
            "Spring\ufb01eld",
            "Peoria",
            "Lincoln",
            "Indianapolis",
            "Armstrong",
            "Hinkle",
            "Breese",
            "Drummond",
            "Slavery",
            "Nebraska",
            "Chicago"
        ],
        "11": [
            "Almon",
            "Robert J. Walker",
            "St. Louis",
            "July",
            "Poor",
            "William H. Bissell",
            "Missouri",
            "Mr. Buchanan",
            "Stringfellow",
            "Dayton",
            "Mr.",
            "Coles County",
            "Independence",
            "Colonel",
            "Speed",
            "British",
            "Douglas",
            "Washington",
            "Never",
            "North",
            "Get",
            "Russia",
            "Mr. Lincoln",
            "Mason",
            "Reeder",
            "Louisville",
            "South",
            "Mr. Douglas",
            "Opposition",
            "Ohio",
            "Haman",
            "Illinois",
            "Platte County",
            "United States",
            "Kentucky",
            "Mr. Scripps",
            "Kansas",
            "Spring\ufb01eld",
            "Mr. Fillmore",
            "Lincoln",
            "Mr. Dayton",
            "Fremont",
            "Great Britain",
            "Dixon",
            "Great"
        ],
        "12": [
            "Buchanan",
            "Herndon",
            "Mace",
            "Nelson",
            "Lecompton",
            "Chase",
            "Dred Scott",
            "New York",
            "Missouri",
            "Does",
            "Such",
            "Indiana",
            "God",
            "Virginia",
            "Mr. Buchanan",
            "Mr.",
            "Abraham",
            "That",
            "Senator Douglas",
            "Independence",
            "Maine",
            "Abraham Lincoln",
            "Stephen",
            "Which",
            "Were",
            "Douglas",
            "Washington",
            "North",
            "Wilson",
            "Mr. Lincoln",
            "Roger",
            "African",
            "South",
            "Welcome",
            "Mr. Herndon",
            "Curtis",
            "Mr. Douglas",
            "American",
            "Illinois",
            "Taney",
            "Nobody",
            "United States",
            "Kentucky",
            "Frequent",
            "Bloomington",
            "Franklin",
            "Wise",
            "Somebody",
            "Kansas",
            "Lincoln",
            "Whenever",
            "Hon",
            "April",
            "Africa",
            "Circuit Court",
            "Chicago",
            "James"
        ],
        "13": [
            "Canton",
            "Lewistown",
            "Egypt",
            "Union County",
            "Charleston",
            "Fulton County",
            "God",
            "Did",
            "Je\ufb00erson",
            "New York",
            "Freeport",
            "English",
            "Mr.",
            "Jonesboro",
            "Coles County",
            "Independence",
            "Africa",
            "Judd",
            "Columbia",
            "Douglas",
            "Marshall County",
            "Mr. Lincoln",
            "Jackson",
            "Union",
            "Mr. Trumbull",
            "Trumbull",
            "MR.",
            "Mr. Douglas",
            "Ottawa",
            "Minnesota",
            "Ohio",
            "Havana",
            "Galesburg",
            "Mason County",
            "Bath",
            "Adams County",
            "Illinois",
            "United States",
            "Whether Mr. Lincoln",
            "Aurora",
            "Henry",
            "Kansas",
            "Lincoln Shields",
            "Judge",
            "Enough",
            "Spring\ufb01eld",
            "Alton",
            "Peoria",
            "Lincoln",
            "Quincy",
            "Madison County",
            "Clinton",
            "Hon",
            "Slavery",
            "Fred",
            "Nebraska",
            "Knox County",
            "Stephenson County"
        ],
        "14": [
            "Brooklyn",
            "Wade",
            "Popular",
            "Awakes",
            "Again",
            "Rev",
            "Sharp",
            "Je\ufb00erson",
            "German",
            "Chase",
            "Corwin",
            "Massachusetts",
            "New York",
            "Stand",
            "English",
            "Certainly",
            "John",
            "England",
            "John Brown",
            "Mr.",
            "Colt",
            "Senator Douglas",
            "Lafayette",
            "Abe Lincoln",
            "Abraham Lincoln",
            "Benjamin Franklin",
            "Thomas Hanks",
            "Alexander Hamilton",
            "Harper",
            "Tubal Cain",
            "Macon County",
            "Norwich",
            "Douglas",
            "Broadway",
            "Washington",
            "North",
            "New England",
            "Mr. Lincoln",
            "Leavenworth",
            "African",
            "Union",
            "Seward",
            "South",
            "Mr. Bancroft",
            "True",
            "Mr. Douglas",
            "Ohio",
            "Macon",
            "Madison",
            "William Cullen Bryant",
            "Mr. Gulliver",
            "Yale College",
            "Illinois",
            "God",
            "United States",
            "Kentucky",
            "Governor Oglesby",
            "Kentuckian",
            "East",
            "Mr. Seward",
            "Kansas",
            "Mr. Bryant",
            "Could",
            "Wrong",
            "George Bancroft",
            "None",
            "Lincoln",
            "Rhode Island",
            "Decatur",
            "Old",
            "Slavery",
            "Mr. Beecher",
            "Chicago"
        ],
        "15": [
            "Mr. Delano",
            "Charleston",
            "Henry Clay",
            "William L. Dayton",
            "Salmon P.",
            "Indiana",
            "Richmond",
            "Benjamin F. Wade",
            "Sumner",
            "Abraham Lincoln",
            "Vermont",
            "Whose",
            "Edward",
            "George",
            "Abe",
            "Douglas",
            "Mr. Lincoln",
            "Seward",
            "Mr. Yancey",
            "George W. Curtis",
            "South",
            "Caleb",
            "Christian",
            "Minnesota",
            "Ohio",
            "Tennessee",
            "Cuba",
            "Spring\ufb01eld",
            "New Jersey",
            "Mr. Dayton",
            "Fremont",
            "Deeply",
            "Michigan",
            "Floyd",
            "Wigwam",
            "Carl Schurz",
            "Mr. Chairman",
            "New York",
            "Texas",
            "John",
            "Virginia",
            "Mr. Buchanan",
            "William H. Seward",
            "Mr.",
            "Mr. Cameron",
            "Divine Providence",
            "Hannibal Hamlin",
            "Jones",
            "John McLean",
            "Maine",
            "John Bell",
            "Cobb",
            "North",
            "Union",
            "Daniel Webster",
            "Mr. Blair",
            "Mr. Jones",
            "Kentucky",
            "Edward Bates",
            "Jacob Collamer",
            "Greeley",
            "Hon",
            "Walker",
            "Simon Cameron",
            "Nebraska",
            "Pennsylvania",
            "Mr. Cartter",
            "Mr. Collamer",
            "Lecompton",
            "Dred Scott",
            "Missouri",
            "Brown",
            "South Carolina",
            "Yancey",
            "Eighth",
            "Men",
            "Sir",
            "Mr. Douglas",
            "New Hampshire",
            "Canvassing",
            "Edward Everett",
            "New York Tribune",
            "Mr. Chase",
            "Wisconsin",
            "Oregon",
            "Mr. Seward",
            "California",
            "Kansas",
            "Mr. Evarts",
            "Mr. Greeley",
            "Lincoln",
            "Mr. Judd",
            "Charles Sumner",
            "Baltimore",
            "William",
            "Massachusetts",
            "District",
            "Independence",
            "Cameron",
            "John C. Breckinridge",
            "Joshua",
            "John C. Fremont",
            "Columbia",
            "Ashmun",
            "Iowa",
            "Illinois",
            "John M. Reed",
            "United States",
            "Bates",
            "Mr. Ashmun",
            "Chicago"
        ],
        "16": [
            "Providence",
            "Drs",
            "Stephens",
            "God",
            "Nothing",
            "Scott",
            "Helper",
            "John Brown",
            "Virginia",
            "Doesn",
            "Mr.",
            "Mr. Bateman",
            "Divine",
            "Abraham Lincoln",
            "Ross",
            "John Bell",
            "Revelation",
            "Harper",
            "Mr. Hamlin",
            "Jesus Christ",
            "Douglas",
            "Magazine",
            "Washington",
            "North",
            "Mr. Lincoln",
            "Men",
            "South",
            "Christian",
            "Mr. Douglas",
            "Georgia",
            "Hurrah",
            "American",
            "Illinois",
            "Mr. Breckinridge",
            "Major John Hay",
            "United States",
            "Mr. Stephens",
            "Spring\ufb01eld",
            "Mr. Bell",
            "Palmer",
            "John C.",
            "Lincoln",
            "Divine Master",
            "Christ",
            "Stephen A. Douglas",
            "America",
            "Chicago"
        ],
        "17": [
            "Columbus",
            "Friends",
            "Yates",
            "Allusion",
            "Charleston",
            "Browning",
            "Je\ufb00erson",
            "German",
            "Indiana",
            "Scotch",
            "Byrne",
            "Richmond",
            "Nicolay",
            "Senator Douglas",
            "Abraham Lincoln",
            "Cleveland",
            "John Tyler",
            "Judd",
            "John M. Hay",
            "Abe",
            "Douglas",
            "Mr. Lincoln",
            "David Davis",
            "Germans",
            "Seward",
            "Mr. Wigfall",
            "South",
            "Lawrenceburgh Mr. Lincoln",
            "Ohio",
            "Ashmore",
            "Major Anderson",
            "Spring\ufb01eld",
            "Mr. Bell",
            "New Jersey",
            "Boyd",
            "Floyd",
            "Weems",
            "Already",
            "Bonham",
            "Greensburgh",
            "Fernando Wood",
            "Solomon",
            "Major Dennis J. Yoohey",
            "New York",
            "Texas",
            "Mr. Buchanan",
            "Divine Providence",
            "Mr.",
            "Je\ufb00erson Davis",
            "Sherlock",
            "Cobb",
            "Howell",
            "Loyalty",
            "Florida",
            "Thompson",
            "Este",
            "Dennison",
            "Alabama",
            "North",
            "Senator Seward",
            "Georgia",
            "Mississippi",
            "Madison",
            "Mr. Breckinridge",
            "Kentucky",
            "Capitol",
            "Albany",
            "Cultivate",
            "Indianapolis",
            "Hon",
            "Italian",
            "Pennsylvania",
            "Morton",
            "Again",
            "Honor",
            "Scott",
            "Heaven",
            "Wilmington",
            "South Carolina",
            "Ladies",
            "Euclid Street",
            "Sir",
            "American",
            "Louisiana",
            "Mr. Seward",
            "Lincoln",
            "Mr. Holt",
            "Independence Hall",
            "Custom House",
            "Baltimore",
            "Wallace",
            "Maryland",
            "Mr. Washburne",
            "Chesnut",
            "Mr. Black",
            "Hammond",
            "Business",
            "Poughkeepsie",
            "Masters",
            "Independence",
            "Mr. Frederick",
            "Robert",
            "Trenton",
            "Washington",
            "Harrisburgh",
            "Cincinnati",
            "Black",
            "Edwin",
            "Bishop",
            "Mr. Stanton",
            "Bu\ufb00alo",
            "Illinois",
            "United States",
            "Baltimore Railroad",
            "Assembly",
            "Ellsworth",
            "Mobile",
            "America",
            "Brethren"
        ],
        "18": [
            "North Carolina",
            "Annapolis",
            "State",
            "Charleston",
            "Simon",
            "Je\ufb00erson",
            "Montgomery Blair",
            "Indiana",
            "Richmond",
            "George",
            "Stephen",
            "Douglas",
            "Mr. Lincoln",
            "Seward",
            "West",
            "Senators",
            "South",
            "Caleb",
            "Ohio",
            "Tennessee",
            "Major Anderson",
            "Northern",
            "Diplomatic Corps",
            "Buchanan",
            "Delaware",
            "Perpetuity",
            "New York",
            "Nothing",
            "Texas",
            "Virginia",
            "Mr. Buchanan",
            "Intelligence",
            "Inaugural",
            "Mr.",
            "Andrew",
            "Clerk",
            "Anderson",
            "Chicago",
            "John Bell",
            "Apprehension",
            "Sumter",
            "Florida",
            "Christianity",
            "Alabama",
            "North",
            "Must",
            "Lord Lyons",
            "Union",
            "Senator Baker",
            "Georgia",
            "Mississippi",
            "Money",
            "Mr. Breckinridge",
            "Edward Bates",
            "Arrangements",
            "War",
            "Foote",
            "Salmon",
            "Hon",
            "Pennsylvania",
            "March",
            "Again",
            "Ferry",
            "Fort Sumter",
            "God",
            "Montgomery",
            "Missouri",
            "May",
            "Heaven",
            "Brown",
            "South Carolina",
            "Harper",
            "British",
            "New England",
            "Roger",
            "Herculean",
            "Mr. Douglas",
            "American",
            "Taney",
            "Louisiana",
            "Oregon",
            "Mr. Seward",
            "Boston",
            "Pierce",
            "Lincoln",
            "Cairo",
            "Nay",
            "Postmaster General",
            "Gideon",
            "Baltimore",
            "Maryland",
            "Beauregard",
            "Unanimity",
            "Talbot",
            "Massachusetts",
            "Judges",
            "Davis",
            "Europe",
            "Independence",
            "Columbia",
            "Fanueil Hall",
            "Mr. Hamlin",
            "Loyal",
            "Bellair",
            "Washington",
            "Avenue",
            "Hicks",
            "Treason",
            "Illinois",
            "United States",
            "Shall",
            "America",
            "Mr. Ashmun",
            "Mr. Forsyth",
            "Mr. Crawford",
            "Great",
            "James"
        ],
        "19": [
            "Morris",
            "North Carolina",
            "Annapolis",
            "Mr. Davis",
            "Indiana",
            "United Colonies",
            "Mr. Defrees",
            "Mr. Lincoln",
            "Jackson",
            "South",
            "Ohio",
            "Francis H. Pierpoint",
            "Rebel",
            "Major Winthrop",
            "Captain",
            "Johnson",
            "Whenever",
            "Providence",
            "Burnett",
            "French",
            "Delaware",
            "Herndon",
            "New York",
            "Texas",
            "Such",
            "Virginia",
            "Mr.",
            "Bayard",
            "Je\ufb00erson Davis",
            "Colonel",
            "Ben Wood",
            "Sumter",
            "Florida",
            "Union",
            "Mr. Trumbull",
            "Garnett",
            "Kentucky",
            "August",
            "Western",
            "Enough",
            "Major General Patterson",
            "Peace",
            "Pennsylvania",
            "Major General McDowell",
            "Mr. Crittenden",
            "Harney",
            "Again",
            "St. Louis",
            "Ferry",
            "Polk",
            "Scott",
            "Missouri",
            "Confederate",
            "Harper",
            "Second",
            "British",
            "Mr. Douglas",
            "Alexandria",
            "American",
            "Third",
            "Mr. Chase",
            "Kennedy",
            "Lincoln",
            "Sterling Price",
            "Reid",
            "Brownell",
            "Much",
            "Cairo",
            "Norton",
            "Patience",
            "Maryland",
            "Winthrop",
            "Rich Mountain",
            "Massachusetts",
            "Mexican",
            "Davis",
            "Europe",
            "Beyond",
            "Independence",
            "George B. McClellan",
            "Defrees",
            "Columbia",
            "Washington",
            "Butler",
            "Thomas",
            "James Jackson",
            "Lyon",
            "Bladensburgh",
            "Illinois",
            "United States",
            "Patterson",
            "Potomac",
            "Buckner",
            "Ellsworth",
            "McClellan",
            "Bright",
            "Greble"
        ],
        "20": [
            "Price",
            "Thomas L. Snead",
            "European",
            "Mr. Davis",
            "French",
            "St. Louis",
            "Britain",
            "German",
            "Joseph",
            "Scott",
            "Her Majesty",
            "Missouri",
            "Paducah",
            "England",
            "Je\ufb00erson City",
            "Mr. Adams",
            "Halleck",
            "Brother",
            "Mr.",
            "Abraham",
            "St.",
            "Europe",
            "Mr. Cameron",
            "Munson",
            "Blu\ufb00",
            "Mr. Charles Francis Adams",
            "Power",
            "John C. Fremont",
            "Colonel",
            "Je\ufb00 Thompson",
            "Brigadier General",
            "Loyal",
            "British",
            "Washington",
            "Port",
            "Wilson",
            "Mr. Lincoln",
            "Jackson",
            "Germans",
            "South",
            "Sigel",
            "Ben McCulloch",
            "St. James",
            "Sherman",
            "Hunter",
            "Holt",
            "Lyon",
            "France",
            "Colonel Blair",
            "American",
            "Hill",
            "Port Royal",
            "Mulligan",
            "United States",
            "Kentucky",
            "Potomac",
            "Blair",
            "August",
            "Buckner",
            "Mr. Seward",
            "California",
            "Colonel Williams",
            "London",
            "Carolina",
            "War",
            "Lincoln",
            "McClellan",
            "Sedalia",
            "Hon",
            "Grant",
            "Fremont",
            "Great Britain",
            "Great"
        ],
        "21": [
            "North Carolina",
            "Charleston",
            "Mr. Adams",
            "John Slidell",
            "Room",
            "Mr. Lincoln",
            "Savannah",
            "South",
            "Tybee Island",
            "Horace Greeley",
            "Ohio",
            "France",
            "Tennessee",
            "Cuba",
            "Captain",
            "Mr. Mason",
            "Capital",
            "Alexander Cummings",
            "Delaware",
            "San Jacinto",
            "New York",
            "Virginia",
            "Mr. Buchanan",
            "Mr.",
            "South America",
            "Mr. Cameron",
            "Lord",
            "Mr. Slidell",
            "Port",
            "Russia",
            "Lord Lyons",
            "Union",
            "Port Royal",
            "Lyons",
            "Kentucky",
            "August",
            "Impulsive",
            "London",
            "Hatteras",
            "Hon",
            "July",
            "Earl Russell",
            "God",
            "Missouri",
            "England",
            "Stanton",
            "Captain Wilkes",
            "Heaven",
            "Christendom",
            "Earl",
            "British",
            "New England",
            "Mason",
            "African",
            "Men",
            "Mr. Cummings",
            "Pollard",
            "American",
            "Harbor",
            "Mr. Chase",
            "Edwin M. Stanton",
            "Mr. Seward",
            "Mr. Greeley",
            "Wilkes",
            "Lincoln",
            "Great Britain",
            "Labor",
            "Maryland",
            "Massachusetts",
            "English",
            "Horace",
            "Davis",
            "Europe",
            "Cameron",
            "Columbia",
            "Washington",
            "Malcontents",
            "Dear Sir",
            "Northampton",
            "Ship Island",
            "Mr. Stanton",
            "Havana",
            "Illinois",
            "United States",
            "Potomac",
            "Accomac",
            "McClellan",
            "America",
            "James M. Mason",
            "Mr. Dawes",
            "Break",
            "Claims",
            "Dixon"
        ],
        "22": [
            "North Carolina",
            "Transportation",
            "Urbana",
            "Charleston",
            "Welles",
            "Culpepper Court-House",
            "Magruder",
            "Mexico",
            "Leesburgh",
            "Richmond",
            "Sumner",
            "Fredericksburg Railroad",
            "Blu\ufb00",
            "Heintzelman",
            "Keyes",
            "Cautious",
            "Mr. Lincoln",
            "Jackson",
            "Savannah",
            "West",
            "Hitchcock",
            "Corinth",
            "Warwick River",
            "Aldie",
            "Merrimac",
            "Richardson",
            "Thornton",
            "Sheridan",
            "Tennessee",
            "Winchester",
            "Captain",
            "Thanksgiving",
            "Grant",
            "Fremont",
            "Manassas Junction",
            "Williamsburgh",
            "Shields",
            "Hanover",
            "York River",
            "Mumfordsville",
            "Mr.",
            "Sedgwick",
            "Roanoke Island",
            "Front Royal",
            "North",
            "Stripped",
            "Geary",
            "Sigel",
            "Snicker",
            "Donelson",
            "Mississippi",
            "Woodbury",
            "Kentucky",
            "August",
            "War",
            "Banks",
            "Ohio Railroad",
            "Acquia Creek",
            "Rosecrans",
            "Chase",
            "Pennsylvania",
            "Again",
            "July",
            "Ferry",
            "Burnside",
            "Wherein",
            "Missouri",
            "May",
            "Stanton",
            "Fredericksburg",
            "Ashby",
            "Harper",
            "Mulberry Island",
            "Orleans",
            "Yorktown",
            "Cumberland",
            "Major General Gar\ufb01eld",
            "Alexandria",
            "Strasburg",
            "Rappahannock",
            "Mr. Chase",
            "Antietam",
            "Nashville",
            "Wool",
            "Lincoln",
            "Blue Ridge",
            "Norfolk",
            "Cairo",
            "Island",
            "Gar\ufb01eld",
            "Baltimore",
            "Change",
            "Maryland",
            "Beauregard",
            "Chester",
            "Grenada",
            "English",
            "St. Philip",
            "Gregory",
            "Halleck",
            "District",
            "James River",
            "John Porter",
            "Blenker",
            "Haymarket",
            "Washington",
            "Forts Jackson",
            "Near Yorktown",
            "CIVILIAN",
            "Thomas",
            "Manassas",
            "Mr. Stanton",
            "Porter",
            "Illinois",
            "United States",
            "Pope",
            "Potomac",
            "Chickahominy",
            "Franklin",
            "Hooker",
            "Fitz John Porter",
            "Chattanooga",
            "McClellan",
            "South Mountain",
            "Randolph",
            "James"
        ],
        "23": [
            "North Carolina",
            "St. John",
            "Mr. F.B",
            "Je\ufb00erson",
            "Frankfort",
            "Mr. Boutwell",
            "Abraham Lincoln",
            "Whereof",
            "George",
            "Little",
            "Mr. Lincoln",
            "Seward",
            "South",
            "Party",
            "Horace Greeley",
            "Mr. Carpenter",
            "Christian",
            "Article",
            "Hodges",
            "States",
            "Ascension",
            "Fernando Wood",
            "New York",
            "Nothing",
            "Texas",
            "Ethiopia",
            "Virginia",
            "Mr.",
            "St.",
            "Carpenter",
            "Florida",
            "Christianity",
            "Alabama",
            "York",
            "Cabinet",
            "Mr. Blair",
            "St. James",
            "Georgia",
            "Mississippi",
            "Rebels",
            "Kentucky",
            "August",
            "Mr. Wood",
            "Lee",
            "Artemus Ward",
            "Martin",
            "Hon",
            "St. Charles",
            "Chase",
            "Pennsylvania",
            "Lafourche",
            "God",
            "Key",
            "St. Marie",
            "Emancipation",
            "South Carolina",
            "Christendom",
            "Orleans",
            "African",
            "St. Bernard",
            "American",
            "Armies",
            "Louisiana",
            "Mr. Chase",
            "Antietam",
            "Mr. Seward",
            "Kennedy",
            "Lincoln",
            "Terre Bonne",
            "Norfolk",
            "Portsmouth",
            "Maryland",
            "Massachusetts",
            "Elizabeth City",
            "Berkely",
            "Columbia",
            "Wood",
            "Washington",
            "Rebellion",
            "Northampton",
            "Treason",
            "Public",
            "Plaquemine",
            "United States",
            "Blair",
            "Book",
            "Accomac",
            "New",
            "McClellan",
            "America",
            "Chicago"
        ],
        "24": [
            "Agitation",
            "Clement L. Vallandigham",
            "Port Hudson",
            "Johnston",
            "Senator Douglas",
            "Did Mr. Everett",
            "Edward",
            "William B. Preston",
            "Seymour",
            "Morel",
            "Bragg",
            "Mr. Lincoln",
            "Jackson",
            "South",
            "Christian",
            "East Tennessee",
            "Ohio",
            "Chancellorsville",
            "Mr. Vallandigham",
            "Spring\ufb01eld",
            "New Jersey",
            "James C. Conkling",
            "Grant",
            "Gettysburg",
            "Pursuit",
            "Murfreesboro",
            "Pemberton",
            "Him",
            "Almighty God",
            "New York",
            "June",
            "Virginia",
            "Mr.",
            "Tullahoma",
            "North",
            "Curtis",
            "Georgia",
            "August",
            "Western",
            "Robert E. Lee",
            "Knoxville",
            "Lee",
            "Albany",
            "Rosecrans",
            "Hon",
            "Pennsylvania",
            "March",
            "Leavitt",
            "Grand Gulf",
            "Thanks",
            "Burnside",
            "Erastus",
            "God",
            "Missouri",
            "Canada",
            "England",
            "Fredericksburg",
            "Keystone",
            "Longstreet",
            "British",
            "Sam",
            "Fourscore",
            "New England",
            "African",
            "Beware",
            "American",
            "Waters",
            "Louisiana",
            "Hayti",
            "Mr. Hollander",
            "New Orleans",
            "Empire",
            "Jersey",
            "Port Gibson",
            "Lincoln",
            "Circuit Court",
            "Maryland",
            "Liberia",
            "Massachusetts",
            "Mr. Conkling",
            "Europe",
            "John C. Breckinridge",
            "Washington",
            "John B. Magruder",
            "Illinois",
            "Vicksburg",
            "United States",
            "Vallandigham",
            "Furthermore",
            "Chattanooga",
            "Hooker",
            "Mr. Louiallier",
            "Great"
        ],
        "25": [
            "Rev",
            "Indiana",
            "Abraham Lincoln",
            "Pardon",
            "Further",
            "Mr. Lincoln",
            "Good",
            "Christian",
            "Massa Linkum",
            "Admit",
            "Yazoo",
            "Tennessee",
            "Mr. Lincoln.",
            "Johnson",
            "Quincy",
            "How",
            "Providence",
            "New York",
            "John",
            "Mr.",
            "Colonel",
            "Mr. Lincolns",
            "Madam",
            "George H. Stuart",
            "Fisk",
            "North",
            "Mercy",
            "General",
            "Newman",
            "Mississippi",
            "Burns",
            "London",
            "War",
            "Hon",
            "Chase",
            "Alley",
            "Waterloo",
            "God",
            "Missouri",
            "Certainly",
            "Stanton",
            "Fredericksburg",
            "Toward",
            "Heaven",
            "Schuyler",
            "Libby",
            "Willie",
            "Sir",
            "Mr. Douglas",
            "Don",
            "Mr. Chase",
            "Antietam",
            "Mr. Seward",
            "Lincoln",
            "Africa",
            "John Todd",
            "Island",
            "Colfax",
            "Hammond",
            "Massachusetts",
            "Mr. Duryea",
            "Europe",
            "Chaplain McCabe",
            "Mr. Alley",
            "Washington",
            "Simply",
            "Thomas",
            "Mr. Stanton",
            "Simple",
            "Bishop James",
            "Illinois",
            "Mr. Stuart",
            "Vicksburg",
            "United States",
            "Duryea",
            "Potomac",
            "Lynn",
            "America"
        ],
        "26": [
            "Alexander Long",
            "Baltimore",
            "Maryland",
            "God",
            "Missouri",
            "Montgomery Blair",
            "Hancock",
            "Richmond",
            "Mr.",
            "Arkansas",
            "Washington",
            "Mr. Lincoln",
            "Union",
            "South",
            "Ohio",
            "Mr. Harris",
            "Mississippi",
            "Meade",
            "Baltimoreans",
            "American",
            "Amnesty",
            "United States",
            "Blair",
            "Tennessee",
            "Speaker Colfax",
            "Atlantic",
            "Eleven",
            "Lincoln",
            "Freedmen",
            "America",
            "A\ufb00airs",
            "Mr. Long",
            "Pennsylvania"
        ],
        "27": [
            "Cady Stanton",
            "State",
            "Clifton House",
            "European",
            "Montgomery Blair",
            "George N. Saunders",
            "Mexico",
            "Richmond",
            "Abraham",
            "Benjamin F. Wade",
            "Cooper Institute",
            "Cleveland",
            "Abraham Lincoln",
            "Mr. Henry J. Raymond",
            "Henry Winter Davis",
            "Mr. Lincoln",
            "West",
            "Horace Greeley",
            "Ohio",
            "France",
            "Frederick Douglass",
            "Andrew Johnson",
            "Tennessee",
            "Cuba",
            "New Jersey",
            "Johnson",
            "William Dennison",
            "Fremont",
            "Grant",
            "Pendleton",
            "Call",
            "Fernando Wood",
            "New York",
            "Nothing",
            "John",
            "Virginia",
            "Mr.",
            "Andrew",
            "Jacob Thompson",
            "New York Times",
            "Mr. John Lellyett",
            "Mr. Clay",
            "Je\ufb00erson Davis",
            "George S. Boutwell",
            "Long",
            "Dennison",
            "Thompson",
            "Alabama",
            "Niagara Falls",
            "Mr. Blair",
            "Wendell",
            "Mississippi",
            "Mr. Pendleton",
            "Kentucky",
            "Greeley",
            "Mr. Lellyett",
            "Niagara",
            "Arguelles",
            "Hon",
            "Chase",
            "John Covode",
            "Clement C. Clay",
            "Major Hay",
            "March",
            "July",
            "Missouri",
            "Canada",
            "Arkansas",
            "Gold",
            "Clay",
            "John M. Ashley",
            "Henry J. Raymond",
            "Men",
            "Sherman",
            "American",
            "Louisiana",
            "Mr. Chase",
            "Boston",
            "Mr. Greeley",
            "Lincoln",
            "Draft",
            "Spanish",
            "Holcombe",
            "Taxation",
            "Baltimore",
            "Almighty Ruler",
            "Maryland",
            "Massachusetts",
            "Occasion",
            "George H. Pendleton",
            "George B.",
            "Davis",
            "District",
            "George B. McClellan",
            "Robert",
            "Washington",
            "Wood",
            "United States",
            "Vallandigham",
            "Blair",
            "Saunders",
            "October",
            "McClellan",
            "Cochrane",
            "Jewett",
            "Chicago"
        ],
        "28": [
            "Indiana",
            "Richmond",
            "Abraham",
            "Johnston",
            "November",
            "Edward",
            "Fessenden",
            "Roost",
            "Mr. Lincoln",
            "Savannah",
            "South",
            "Christian",
            "Mr. Carpenter",
            "Ohio",
            "Pitt Fessenden",
            "Mr. Fessenden",
            "Sheridan",
            "Tennessee",
            "Grant",
            "Petersburgh",
            "Providence",
            "Mr. Case",
            "Memphis",
            "Virginia",
            "Mr.",
            "Maine",
            "Florida",
            "North",
            "Georgia",
            "Atlanta",
            "Augusta",
            "Chronicle",
            "Kentucky",
            "Lee",
            "Hampton Roads",
            "Alexander H. Stephens",
            "Arguelles",
            "Hon",
            "Chase",
            "Mr. Francis",
            "March",
            "Bermuda Hundred",
            "July",
            "God",
            "Missouri",
            "Canada",
            "Fernandina",
            "Rapidan",
            "Hood",
            "Pensacola",
            "Sherman",
            "James Speed",
            "Dalton",
            "American",
            "Taney",
            "Case",
            "Mr. Chase",
            "Mr. Seward",
            "Nashville",
            "Lincoln",
            "Great Britain",
            "Hugh McCulloch",
            "Norfolk",
            "Mr. Stephens",
            "Much",
            "David Todd",
            "Kilpatrick",
            "William",
            "Campbell",
            "Davis",
            "Europe",
            "Mr. Hunter",
            "Small",
            "James River",
            "River Queen",
            "Butler",
            "Thomas",
            "Hunter",
            "Vicksburg",
            "Illinois",
            "United States",
            "Potomac",
            "Blair",
            "Charles",
            "Canby",
            "Mobile",
            "April"
        ],
        "29": [
            "North Carolina",
            "March",
            "Goldsboro",
            "Charleston",
            "Campbell",
            "Ord",
            "Virginia",
            "Scho\ufb01eld",
            "Richmond",
            "Weitzel",
            "Mr.",
            "Jesus",
            "Johnston",
            "Lord",
            "South Carolina",
            "River Queen",
            "Columbia",
            "Warren",
            "Though",
            "Washington",
            "North",
            "Mr. Lincoln",
            "Men",
            "African",
            "Union",
            "Sherman",
            "Paci\ufb01c",
            "Public",
            "Mr. Stanton",
            "Linkum",
            "South",
            "Georgia",
            "Battles",
            "Meade",
            "American",
            "Bentonville",
            "Bless",
            "Sheridan",
            "United States",
            "Louisiana",
            "Lee",
            "Fayetteville",
            "New",
            "Lincoln",
            "America",
            "Cannon",
            "April",
            "Grant",
            "Glory",
            "James"
        ],
        "30": [
            "Laura",
            "Columbus",
            "Yates",
            "Gurley",
            "Rev",
            "Tom Taylor",
            "Welles",
            "Funereal",
            "Moderate",
            "Smith",
            "Miss Harrill",
            "Broken",
            "Lafayette",
            "Junius Brutus Booth",
            "Abraham Lincoln",
            "Cleveland",
            "Edward",
            "Major Augustus Seward",
            "George",
            "Douglas",
            "Mr. Lincoln",
            "Seward",
            "South",
            "Christian",
            "George A. Atzerodt",
            "Ohio",
            "McIlvaine",
            "Joseph Hooker",
            "France",
            "Booth",
            "Sergeant",
            "Macmillan",
            "Spring\ufb01eld",
            "New Jersey",
            "Johnson",
            "Mr. Mason",
            "Grant",
            "Providence",
            "David E. Harold",
            "Him",
            "Almighty God",
            "New York",
            "John",
            "Humble",
            "Virginia",
            "Mr.",
            "Andrew",
            "St.",
            "Washburne",
            "Pittsburg Railroad",
            "Chicago",
            "Dennison",
            "David C. Harold",
            "Paris",
            "Union",
            "Paci\ufb01c",
            "General",
            "Co\ufb00roth",
            "Lewis Payne Powell",
            "Tribune",
            "Scripture",
            "Capitol",
            "London",
            "Albany",
            "Samuel Mudd",
            "Indianapolis",
            "Hon",
            "Large",
            "Atzerodt",
            "Waterloo",
            "Harris",
            "Robinson",
            "Spangler",
            "God",
            "Millions",
            "Canada",
            "Conscience",
            "England",
            "Stanton",
            "Samuel Arnold",
            "Queen",
            "Willie",
            "Harold",
            "Brough",
            "British",
            "Major Rathbone",
            "William Garratt",
            "John Bigelow",
            "Barnes",
            "Men",
            "African",
            "Mr. McCulloch",
            "Edward Spangler",
            "American",
            "Herald",
            "Mr. Seward",
            "Speaker Colfax",
            "Mr. Colfax",
            "Goldwin Smith",
            "Lincoln",
            "Miss Harris",
            "Bishop Simpson",
            "Keene",
            "Miss Laura Keene",
            "Wade",
            "Baltimore",
            "Slain",
            "Tenth",
            "Colfax",
            "Maryland",
            "Step",
            "Payne",
            "Kensington Station",
            "Massachusetts",
            "Presbyterian",
            "English",
            "Mary E. Surratt",
            "Europe",
            "Mr. Johnson",
            "Wilkes Booth",
            "Mudd",
            "Robert",
            "Michael O",
            "Oglesby",
            "Hence",
            "Washington",
            "Cincinnati",
            "Thomas",
            "Bowery",
            "Mr. Peterson",
            "Bishop",
            "MR.",
            "John Wilkes Booth",
            "Morgan",
            "Review",
            "Bu\ufb00alo",
            "Illinois",
            "United States",
            "Mr. Frederick Seward",
            "Mr. Bigelow",
            "Mr. Ashmun",
            "America",
            "Fenton",
            "April",
            "Worthington",
            "Great",
            "Charles County",
            "James"
        ]
    }
}